COPYING
MANIFEST.in
README.rst
setup.py
labmanager/__init__.py
labmanager/api.py
labmanager/config.py
labmanager/loghandler.py
labmanager/shell.py
lmsh.egg-info/PKG-INFO
lmsh.egg-info/SOURCES.txt
lmsh.egg-info/dependency_links.txt
lmsh.egg-info/entry_points.txt
lmsh.egg-info/requires.txt
lmsh.egg-info/top_level.txt