Metadata-Version: 1.0
Name: lmsh
Version: 0.1.4
Summary: Command line interface to Lab Manager SOAP API
Home-page: https://github.com/jamesls/labmanager-shell
Author: James Saryerwinnie
Author-email: jlsnpi@gmail.com
License: BSD
Keywords: labmanager
Platform: UNKNOWN
Classifier: Development Status :: 3 - Alpha
Classifier: License :: OSI Approved :: BSD License
